{
  "Kota NEET UG 2026 Master Pro 1": {
    "category": "NEET",
    "subjects": {
      "ZOOLOGY": { "uids": ["76O3VNLX"], "name": "ZOOLOGY" },
      "Physics": { "uids": ["W79Z40CU"], "name": "Physics" },
      "BOTANY": { "uids": ["SC406CEW"], "name": "BOTANY" },
      "Organic Chemistry": { "uids": ["UUMHOI91"], "name": "Organic Chemistry" }
    }
  },
  "Kota NEET UG 2026 Master Pro 1 (H)": {
    "category": "NEET",
    "subjects": {
      "Physics": { "uids": ["MVRJ61XW"], "name": "Physics" },
      "ZOOLOGY": { "uids": ["IMO0KSM2"], "name": "ZOOLOGY" },
      "BOTANY": { "uids": ["8YA8R4CE"], "name": "BOTANY" },
      "Organic Chemistry": { "uids": ["MOIXLBSC"], "name": "Organic Chemistry" }
    }
  },
  "Kota NEET UG 2026 Conquer 1": {
    "category": "NEET",
    "subjects": {
      "PHYSICS - 1": { "uids": ["JV7J5WUV"], "name": "PHYSICS - 1" },
      "Organic Chemistry": { "uids": ["WZIKULJI"], "name": "Organic Chemistry" },
      "ZOOLOGY": { "uids": ["GTNE6JAC"], "name": "ZOOLOGY" },
      "PHYSICS - 2": { "uids": ["BX2YEI2Z"], "name": "PHYSICS - 2" },
      "Physical Chemistry": { "uids": ["O93DCAUD"], "name": "Physical Chemistry" }
    }
  },
  "Kota NEET UG 2026 Master Pro Plus": {
    "category": "NEET",
    "subjects": {
      "PHYSICS": { "uids": ["4FTKSFCA"], "name": "PHYSICS" },
      "Physical Chemistry": { "uids": ["85Y2BQ82"], "name": "Physical Chemistry" },
      "BOTANY": { "uids": ["7K6P88WU"], "name": "BOTANY" }
    }
  },
  "Kota NEET UG 2027 Growth 1": {
    "category": "NEET",
    "subjects": {
      "PHYSICAL CHEMISTRY": { "uids": ["WGWZ33QP"], "name": "PHYSICAL CHEMISTRY" },
      "ZOOLOGY": { "uids": ["O97GFUCX"], "name": "ZOOLOGY" },
      "PHYSICS": { "uids": ["7PO1TIBF"], "name": "PHYSICS" },
      "Botany": { "uids": ["3W5XGVRV"], "name": "Botany" }
    }
  },
  "Patna NEET UG 2026 Conquer 1": {
    "category": "NEET",
    "subjects": {
      "Zoology": { "uids": ["IW75K8JV"], "name": "Zoology" },
      "Chemistry": { "uids": ["5WTX9CE3"], "name": "Chemistry" },
      "Physics": { "uids": ["9XHQWNU2"], "name": "Physics" },
      "Botany": { "uids": ["IPG9ROEY"], "name": "Botany" },
      "Organic Chemistry": { "uids": ["GWB0EH1H"], "name": "Organic Chemistry" }
    }
  },
  "Kota NEET UG 2027 Growth 2": {
    "category": "NEET",
    "subjects": {
      "BOTANY": { "uids": ["6QMJYWEV"], "name": "BOTANY" },
      "PHYSICS": { "uids": ["U35SG5JG"], "name": "PHYSICS" },
      "PHYSICAL CHEMISTRY": { "uids": ["733BDD9B"], "name": "PHYSICAL CHEMISTRY" }
    }
  },
  "Kota NEET UG 2026 Excel 1": {
    "category": "NEET",
    "subjects": {
      "Botany": { "uids": ["1QEB3XKT"], "name": "Botany" },
      "PHYSICAL CHEMISTRY": { "uids": ["A5M4WOGJ"], "name": "PHYSICAL CHEMISTRY" },
      "PHYSICS": { "uids": ["U120QTWR"], "name": "PHYSICS" },
      "Organic Chemistry": { "uids": ["JP23HMW2"], "name": "Organic Chemistry" }
    }
  },
  "Sikar NEET UG 2026 Excel 2": {
    "category": "NEET",
    "subjects": {
      "Physics - 1": { "uids": ["78Q4KLVP", "DTK8L8AL"], "name": "Physics - 1" },
      "Physics - 2": { "uids": ["TKJW0Z4A"], "name": "Physics - 2" },
      "Physics - 3": { "uids": ["JURZSRUV"], "name": "Physics - 3" },
      "Botany - 1": { "uids": ["PLJ1KI0X"], "name": "Botany - 1" },
      "Botany - 2": { "uids": ["LQA69TPZ"], "name": "Botany - 2" },
      "Organic Chemistry - 1": { "uids": ["T4JA7Y7C"], "name": "Organic Chemistry - 1" },
      "Organic Chemistry - 2": { "uids": ["HFPRRHHQ"], "name": "Organic Chemistry - 2" },
      "Physical Chemistry": { "uids": ["9KGMJCNB"], "name": "Physical Chemistry" },
      "Zoology": { "uids": ["EMAH5CX4"], "name": "Zoology" }
    }
  },
  "Kanpur NEET UG 2026 Conquer 1": {
    "category": "NEET",
    "subjects": {
      "Physics": { "uids": ["I0J2DGEX"], "name": "Physics" },
      "Biology": { "uids": ["K87IAHFL"], "name": "Biology" },
      "Chemistry": { "uids": ["VIVEQV9V"], "name": "Chemistry" }
    }
  },
  "Kanpur NEET UG 2026 Conquer Pro 1": {
    "category": "NEET",
    "subjects": {
      "Biology": { "uids": ["UMJGOQBZ"], "name": "Biology" },
      "Chemistry": { "uids": ["9X9M36A7"], "name": "Chemistry" },
      "Physics": { "uids": ["5FWIA108"], "name": "Physics" }
    }
  },
  "Kanpur NEET UG 2026 Conquer 2": {
    "category": "NEET",
    "subjects": {
      "Chemistry": { "uids": ["0PKMMLWD"], "name": "Chemistry" },
      "Physics": { "uids": ["GFIISCEX"], "name": "Physics" },
      "Biology": { "uids": ["SBGF24AT"], "name": "Biology" }
    }
  },
  "Kanpur NEET UG 2026 Conquer 3": {
    "category": "NEET",
    "subjects": {
      "Biology": { "uids": ["E94CU8TC"], "name": "Biology" },
      "Chemistry": { "uids": ["OIYGXWN8"], "name": "Chemistry" },
      "Physics": { "uids": ["M1Z5HLW7"], "name": "Physics" }
    }
  },
  "Kanpur NEET UG 2027 Growth 1": {
    "category": "NEET",
    "subjects": {
      "Chemistry": { "uids": ["IMTSMAR0"], "name": "Chemistry" },
      "Biology": { "uids": ["93P01ERZ"], "name": "Biology" },
      "Physics": { "uids": ["8BCTOJP7"], "name": "Physics" }
    }
  },
  "Lajpat Nagar NEET UG 2026 Conquer 1": {
    "category": "NEET",
    "subjects": {
      "Botany": { "uids": ["GR03C2AJ"], "name": "Botany" },
      "Chemistry": { "uids": ["9LCMKAJA"], "name": "Chemistry" },
      "Physics": { "uids": ["D4NTFI0Z"], "name": "Physics" }
    }
  },
  "Lajpat Nagar NEET UG 2026 Excel 1": {
    "category": "NEET",
    "subjects": {
      "Botany": { "uids": ["C52JVMT5"], "name": "Botany" },
      "Chemistry": { "uids": ["4S5L4DLW"], "name": "Chemistry" },
      "Physics": { "uids": ["1QO99U9M"], "name": "Physics" }
    }
  },
  "Kota NEET UG 2026 Excel 2": {
    "category": "NEET",
    "subjects": {
      "Physics": { "uids": ["K9V2XW3T"], "name": "Physics" },
      "Botany": { "uids": ["N7P4QJ8R"], "name": "Botany" },
      "Organic Chemistry": { "uids": ["F3M8TK2Y"], "name": "Organic Chemistry" },
      "Zoology": { "uids": ["H6L9Z5PU"], "name": "Zoology" }
    }
  },
  "Patna NEET UG 2027 Growth 1": {
    "category": "NEET",
    "subjects": {
      "Physics": { "uids": ["P2Q7R4VM"], "name": "Physics" },
      "Botany": { "uids": ["T8N3K6WX"], "name": "Botany" },
      "Zoology": { "uids": ["Y5J1M9ZF"], "name": "Zoology" },
      "Physical Chemistry": { "uids": ["R4H8T2QD"], "name": "Physical Chemistry" }
    }
  },
  "Sikar NEET UG 2026 Master Pro 1": {
    "category": "NEET",
    "subjects": {
      "Physics": { "uids": ["X3G9L7HB"], "name": "Physics" },
      "Botany": { "uids": ["Z6T2P8KM"], "name": "Botany" },
      "Zoology": { "uids": ["W9R5V3JY"], "name": "Zoology" },
      "Organic Chemistry": { "uids": ["Q4M7N2TF"], "name": "Organic Chemistry" }
    }
  },
  "Indore MM NEET UG 2026 Conquer 1": {
    "category": "NEET",
    "subjects": {
      "Botany": { "uids": ["0DMZ243O"], "name": "Botany" },
      "Zoology": { "uids": ["IFKBDMWK"], "name": "Zoology" },
      "Physics": { "uids": ["2N6L29ZI"], "name": "Physics" },
      "Inorganic Chemistry": { "uids": ["EM5WC6A4"], "name": "Inorganic Chemistry" },
      "Physical Chemistry": { "uids": ["EHC959TO"], "name": "Physical Chemistry" },
      "Organic Chemistry": { "uids": ["9NIJ3CWL"], "name": "Organic Chemistry" }
    }
  },
  "Indore MM NEET UG 2026 Conquer 2": {
    "category": "NEET",
    "subjects": {
      "Physical Chemistry": { "uids": ["4XMIITSV"], "name": "Physical Chemistry" },
      "Botany": { "uids": ["WNQM3ODG"], "name": "Botany" },
      "Inorganic Chemistry": { "uids": ["Y38BVENQ"], "name": "Inorganic Chemistry" },
      "Zoology": { "uids": ["EL4OV9KP"], "name": "Zoology" },
      "Physics": { "uids": ["RPULVPJT"], "name": "Physics" }
    }
  },
  "M NEET UG 2026 Conquer 3": {
    "category": "NEET",
    "subjects": {
      "Zoology": { "uids": ["HOMF0KKZ"], "name": "Zoology" },
      "Physical Chemistry": { "uids": ["PR6MCXPE"], "name": "Physical Chemistry" },
      "Botany": { "uids": ["9XMW25JS"], "name": "Botany" },
      "Physics": { "uids": ["PGHHFFZU"], "name": "Physics" },
      "Inorganic Chemistry": { "uids": ["TYUKT19U"], "name": "Inorganic Chemistry" }
    }
  },
  "Indore MM NEET(Hindi) UG 2026 Conquer 1": {
    "category": "NEET",
    "subjects": {
      "Inorganic Chemistry": { "uids": ["ODNTAUT8"], "name": "Inorganic Chemistry" },
      "Physics": { "uids": ["9DSPZA78"], "name": "Physics" },
      "Botany": { "uids": ["N9BVEQL4"], "name": "Botany" },
      "Zoology": { "uids": ["6877HZDZ"], "name": "Zoology" },
      "Physical Chemistry": { "uids": ["OP3470GD"], "name": "Physical Chemistry" }
    }
  },
  "Indore MM NEET UG 2026 Excel 1": {
    "category": "NEET",
    "subjects": {
      "Physics": { "uids": ["YEZ0DU5Z"], "name": "Physics" },
      "Botany": { "uids": ["9JU00VDY"], "name": "Botany" },
      "Zoology": { "uids": ["CSFPPZ00"], "name": "Zoology" },
      "Organic Chemistry": { "uids": ["OWJBL7PP"], "name": "Organic Chemistry" }
    }
  },
  "Indore MM NEET UG 2026 Excel 2": {
    "category": "NEET",
    "subjects": {
      "Physics": { "uids": ["QDSR8RNW"], "name": "Physics" },
      "Zoology": { "uids": ["BAVEH376"], "name": "Zoology" },
      "Inorganic Chemistry": { "uids": ["EJXRN9G3"], "name": "Inorganic Chemistry" },
      "Botany": { "uids": ["P4L962XE"], "name": "Botany" },
      "Organic Chemistry": { "uids": ["UXK8FFBU"], "name": "Organic Chemistry" }
    }
  },
  "Indore MM NEET UG 2027 Growth 1": {
    "category": "NEET",
    "subjects": {
      "Physics": { "uids": ["8K9K0L6J"], "name": "Physics" },
      "Physical Chemistry": { "uids": ["FIQN62EJ"], "name": "Physical Chemistry" },
      "Botany": { "uids": ["7EKGUXQN"], "name": "Botany" },
      "Zoology": { "uids": ["7U4PY3VP"], "name": "Zoology" }
    }
  },
  "Lucknow HZ NEET UG 2026 Conquer 1": {
    "category": "NEET",
    "subjects": {
      "Zoology": { "uids": ["29VIX2NA"], "name": "Zoology" },
      "Chemistry": { "uids": ["2NBISFGH", "NM1EWPK9"], "name": "Chemistry" },
      "Physics": { "uids": ["KF7G2O5X"], "name": "Physics" }
    }
  },
  "Lucknow HZ NEET UG 2026 Conquer 2": {
    "category": "NEET",
    "subjects": {
      "Physics": { "uids": ["2FL4BUAC"], "name": "Physics" },
      "Zoology": { "uids": ["X79SVBDV"], "name": "Zoology" },
      "Botany": { "uids": ["5H38PXJQ"], "name": "Botany" },
      "Chemistry": { "uids": ["NM1EWPK9"], "name": "Chemistry" }
    }
  },
  "Lucknow HZ NEET UG 2026 Excel 1": {
    "category": "NEET",
    "subjects": {
      "Zoology": { "uids": ["HDXP662A"], "name": "Zoology" },
      "Physics": { "uids": ["5HSLPXK9"], "name": "Physics" },
      "Chemistry": { "uids": ["4ZVNIE49"], "name": "Chemistry" },
      "Botany": { "uids": ["TBKR9CUU"], "name": "Botany" }
    }
  },
  "Chandigarh NEET UG 2026 Conquer 1": {
    "category": "NEET",
    "subjects": {
      "Botany": { "uids": ["49TJE8T4"], "name": "Botany" },
      "Chemistry": { "uids": ["BPZZOX50"], "name": "Chemistry" },
      "Physics - 1": { "uids": ["P0504OC1"], "name": "Physics - 1" },
      "Zoology": { "uids": ["XG8GK8DV"], "name": "Zoology" },
      "Physics - 2": { "uids": ["MXC4XIOQ"], "name": "Physics - 2" }
    }
  },
  "Chandigarh NEET UG 2026 Conquer 2": {
    "category": "NEET",
    "subjects": {
      "Physics - 1": { "uids": ["GNMUTEL5"], "name": "Physics - 1" },
      "Zoology": { "uids": ["8J2ORWV2"], "name": "Zoology" },
      "Physics - 2": { "uids": ["2WWG5PIL"], "name": "Physics - 2" },
      "Chemistry": { "uids": ["BHUCOWB9"], "name": "Chemistry" },
      "Botany": { "uids": ["OF0F3W8M"], "name": "Botany" }
    }
  },
  "Chandigarh NEET UG 2026 Excel 1": {
    "category": "NEET",
    "subjects": {
      "Zoology": { "uids": ["LJL8PDK6"], "name": "Zoology" },
      "Chemistry": { "uids": ["NUD0Z9A9"], "name": "Chemistry" },
      "Botany": { "uids": ["W18I345R"], "name": "Botany" },
      "Physics": { "uids": ["UG67Q967"], "name": "Physics" }
    }
  },
  "Chandigarh NEET UG 2026 Excel 2": {
    "category": "NEET",
    "subjects": {
      "Physics": { "uids": ["0J618FO1"], "name": "Physics" },
      "Chemistry": { "uids": ["KIILRU78"], "name": "Chemistry" }
    }
  },
  "Chandigarh NEET UG 2027 Growth 1": {
    "category": "NEET",
    "subjects": {
      "Botany": { "uids": ["CA9S0P1R"], "name": "Botany" },
      "Chemistry": { "uids": ["UNO8PVVS"], "name": "Chemistry" },
      "Zoology": { "uids": ["VZE6LSXM"], "name": "Zoology" },
      "Physics": { "uids": ["U7YPELBZ"], "name": "Physics" }
    }
  },
  "Chandigarh NEET UG 2027 Growth 2": {
    "category": "NEET",
    "subjects": {
      "Chemistry": { "uids": ["OW2SHMO1"], "name": "Chemistry" },
      "Botany": { "uids": ["8EB083WW"], "name": "Botany" },
      "Physics": { "uids": ["KL66O9Z0"], "name": "Physics" },
      "Zoology": { "uids": ["7G6NG4OA"], "name": "Zoology" }
    }
  },
  "Janakpuri NEET UG 2026 Excel 1": {
    "category": "NEET",
    "subjects": {
      "Zoology": { "uids": ["NQDS2Q91"], "name": "Zoology" },
      "Physics": { "uids": ["1AIR1XSU"], "name": "Physics" },
      "Chemistry": { "uids": ["9HVUORZZ"], "name": "Chemistry" },
      "Botany": { "uids": ["T7SNJXOQ"], "name": "Botany" }
    }
  },
  "Janakpuri NEET UG 2026 Conquer 1": {
    "category": "NEET",
    "subjects": {
      "Chemistry": { "uids": ["J9N1I90O"], "name": "Chemistry" },
      "Botany": { "uids": ["8K9SXJ4M"], "name": "Botany" },
      "Physics": { "uids": ["WG1S8UWP"], "name": "Physics" },
      "Zoology": { "uids": ["K9BQWU0H"], "name": "Zoology" }
    }
  },
  "Janakpuri NEET UG 2026 Conquer 2": {
    "category": "NEET",
    "subjects": {
      "Physics": { "uids": ["IRHF6N7C"], "name": "Physics" },
      "Botany": { "uids": ["EP62T6ML"], "name": "Botany" },
      "Chemistry": { "uids": ["O6V55RP4"], "name": "Chemistry" },
      "Zoology": { "uids": ["82ASS2MG"], "name": "Zoology" }
    }
  },
  "Janakpuri NEET UG 2026 Excel 2": {
    "category": "NEET",
    "subjects": {
      "Chemistry": { "uids": ["C04ICMWH"], "name": "Chemistry" },
      "Physics": { "uids": ["KG7JLVAM"], "name": "Physics" },
      "Botany": { "uids": ["ZV3T67XC"], "name": "Botany" }
    }
  },
  "Janakpuri NEET UG 2027 Growth 1": {
    "category": "NEET",
    "subjects": {
      "Botany": { "uids": ["XVWGWTKI"], "name": "Botany" },
      "Physics": { "uids": ["GQSW2C6W"], "name": "Physics" },
      "Chemistry": { "uids": ["6D6E0G63"], "name": "Chemistry" },
      "Zoology": { "uids": ["9CJSAP77"], "name": "Zoology" }
    }
  },
  "Dwarka NEET UG 2026 Conquer 1": {
    "category": "NEET",
    "subjects": {
      "Botany": { "uids": ["LG8XWFNF"], "name": "Botany" },
      "Chemistry": { "uids": ["90TW83WT"], "name": "Chemistry" },
      "Zoology": { "uids": ["GI3XML1D"], "name": "Zoology" },
      "Physics": { "uids": ["10U27ZVS"], "name": "Physics" }
    }
  },
  "Dwarka NEET UG 2027 Growth 1": {
    "category": "NEET",
    "subjects": {
      "Chemistry": { "uids": ["KFEXG3ZA"], "name": "Chemistry" },
      "Physics": { "uids": ["S04648S7"], "name": "Physics" },
      "Botany": { "uids": ["7IEJFBPQ"], "name": "Botany" },
      "Zoology": { "uids": ["SMAYH8CL"], "name": "Zoology" }
    }
  },
  "Dwarka NEET UG 2026 Excel 1": {
    "category": "NEET",
    "subjects": {
      "Botany": { "uids": ["5SKYDGUN"], "name": "Botany" },
      "Chemistry": { "uids": ["L0XD55PK", "QSP6FSSC"], "name": "Chemistry" },
      "Zoology": { "uids": ["I2KJSZZO"], "name": "Zoology" },
      "Physics": { "uids": ["0DHJ8U2P"], "name": "Physics" }
    }
  },
  "Dwarka NEET UG 2026 Excel 2": {
    "category": "NEET",
    "subjects": {
      "Physics": { "uids": ["0DHJ8U2P", "20TTLG63"], "name": "Physics" },
      "Zoology": { "uids": ["HLQNHH5F"], "name": "Zoology" }
    }
  },
  "Noida NEET UG 2026 Conquer 1": {
    "category": "NEET",
    "subjects": {
      "Botany": { "uids": ["Y5372JFY"], "name": "Botany" },
      "Physics": { "uids": ["32NBYAEW"], "name": "Physics" },
      "Chemistry": { "uids": ["84DXU3P5"], "name": "Chemistry" },
      "Zoology": { "uids": ["W4RGGFTZ"], "name": "Zoology" }
    }
  },
  "Noida NEET UG 2026 Conquer 3": {
    "category": "NEET",
    "subjects": {
      "Zoology": { "uids": ["ZDAOJX0G"], "name": "Zoology" },
      "Botany": { "uids": ["UQZ4JGQB"], "name": "Botany" },
      "Chemistry": { "uids": ["Q6VGN20F"], "name": "Chemistry" },
      "Physics": { "uids": ["NJ9H1MO5"], "name": "Physics" }
    }
  },
  "Noida NEET UG 2027 Growth 1": {
    "category": "NEET",
    "subjects": {
      "Zoology": { "uids": ["KHONCFGX"], "name": "Zoology" },
      "Physics": { "uids": ["TNMRX79S"], "name": "Physics" },
      "Botany": { "uids": ["MZ9492T7"], "name": "Botany" },
      "Chemistry": { "uids": ["GC87L2J3"], "name": "Chemistry" }
    }
  },
  "Noida NEET UG 2027 Growth 2": {
    "category": "NEET",
    "subjects": {
      "Zoology": { "uids": ["KHONCFGX"], "name": "Zoology" },
      "Physics - 1": { "uids": ["TNMRX79S"], "name": "Physics - 1" },
      "Botany - 1": { "uids": ["DRADGQ5K"], "name": "Botany - 1" },
      "Physics - 2": { "uids": ["JQIPFRFR"], "name": "Physics - 2" },
      "Chemistry - 1": { "uids": ["B6XTP124"], "name": "Chemistry - 1" },
      "Botany - 2": { "uids": ["MZ9492T7"], "name": "Botany - 2" },
      "Chemistry - 2": { "uids": ["GC87L2J3"], "name": "Chemistry - 2" }
    }
  },
  "Noida NEET UG 2026 Excel 1": {
    "category": "NEET",
    "subjects": {
      "Zoology": { "uids": ["XH4YP50R"], "name": "Zoology" },
      "Physics": { "uids": ["Y2MJQCAH"], "name": "Physics" },
      "Botany": { "uids": ["5K0V20CP"], "name": "Botany" },
      "Chemistry": { "uids": ["3591Z2O4"], "name": "Chemistry" }
    }
  },
  "Noida NEET UG 2026 Excel 2": {
    "category": "NEET",
    "subjects": {
      "Zoology": { "uids": ["7KD9LX5Q"], "name": "Zoology" },
      "Physics": { "uids": ["73FNIGSG"], "name": "Physics" },
      "Botany": { "uids": ["9DMPD78O"], "name": "Botany" },
      "Chemistry": { "uids": ["XA6VMVJI"], "name": "Chemistry" }
    }
  },
  "Ahmedabad NEET UG 2026 Conquer 1": {
    "category": "NEET",
    "subjects": {
      "Physics": { "uids": ["L7U5S1FX", "9MV6BHOD"], "name": "Physics" },
      "Zoology": { "uids": ["EFC38WHF"], "name": "Zoology" },
      "Chemistry": { "uids": ["MGL2GVJM", "PMD65U3R"], "name": "Chemistry" },
      "Biology": { "uids": ["37X89ZOF"], "name": "Biology" }
    }
  },
  "Ahmedabad NEET UG 2026 Conquer 2": {
    "category": "NEET",
    "subjects": {
      "Physics": { "uids": ["V2K9P3HM"], "name": "Physics" },
      "Zoology": { "uids": ["N8J4T6QR"], "name": "Zoology" },
      "Chemistry": { "uids": ["X5P7M2WF"], "name": "Chemistry" },
      "Botany": { "uids": ["Q3T8L9VK"], "name": "Botany" }
    }
  },
  "Pune NEET UG 2026 Conquer 1": {
    "category": "NEET",
    "subjects": {
      "Physics": { "uids": ["P4L2ODSR"], "name": "Physics" },
      "Zoology": { "uids": ["EG2Y5NPF"], "name": "Zoology" },
      "Chemistry": { "uids": ["WYKGIAGO"], "name": "Chemistry" },
      "Botany": { "uids": ["NUJLJ8SX"], "name": "Botany" }
    }
  },
  "Pune NEET UG 2026 Conquer 2": {
    "category": "NEET",
    "subjects": {
      "Botany": { "uids": ["MOTSFFCH"], "name": "Botany" },
      "Chemistry": { "uids": ["SM6KS9JE"], "name": "Chemistry" },
      "Physics": { "uids": ["PCMUSI9X"], "name": "Physics" },
      "Zoology": { "uids": ["NTW45ARJ"], "name": "Zoology" }
    }
  },
  "Pune NEET UG 2026 Excel 1": {
    "category": "NEET",
    "subjects": {
      "Chemistry": { "uids": ["KANXSY1S"], "name": "Chemistry" },
      "Botany": { "uids": ["UXR6ZODA"], "name": "Botany" },
      "Zoology": { "uids": ["45G7TM29"], "name": "Zoology" },
      "Physics": { "uids": ["B32GE8RQ"], "name": "Physics" }
    }
  },
  "Pune NEET UG 2026 Excel 2": {
    "category": "NEET",
    "subjects": {
      "Physics": { "uids": ["17IKM7C3"], "name": "Physics" },
      "Zoology": { "uids": ["TIEUI26F"], "name": "Zoology" },
      "Botany": { "uids": ["5447DIMG"], "name": "Botany" },
      "Chemistry": { "uids": ["3GQV0R5D"], "name": "Chemistry" }
    }
  },
  "Pune NEET UG 2026 Excel 4": {
    "category": "NEET",
    "subjects": {
      "Physics": { "uids": ["8LNYG6PI"], "name": "Physics" },
      "Zoology": { "uids": ["A8RKA5PA"], "name": "Zoology" },
      "Chemistry": { "uids": ["PNZ0808Y"], "name": "Chemistry" },
      "Botany": { "uids": ["5GOOGA5Q"], "name": "Botany" }
    }
  },
  "Pune NEET UG 2027 Growth 1": {
    "category": "NEET",
    "subjects": {
      "Botany": { "uids": ["X1QE6L3Q"], "name": "Botany" },
      "Physics": { "uids": ["6KXBB15T"], "name": "Physics" },
      "Zoology": { "uids": ["3C0JCE46"], "name": "Zoology" },
      "Chemistry": { "uids": ["9TX1V6NU"], "name": "Chemistry" }
    }
  },
  "Pune NEET UG 2027 Growth 4": {
    "category": "NEET",
    "subjects": {
      "Physics": { "uids": ["WDNWAA6J"], "name": "Physics" },
      "Botany": { "uids": ["QW5MHN41"], "name": "Botany" },
      "Zoology": { "uids": ["SL0J8UM7"], "name": "Zoology" },
      "Chemistry": { "uids": ["VQ9MQ4CS"], "name": "Chemistry" }
    }
  },
  "Jodhpur NEET UG 2026 Conquer 1": {
    "category": "NEET",
    "subjects": {
      "Physics": { "uids": ["XTV45MUL"], "name": "Physics" },
      "Botany": { "uids": ["YB2GUPIG", "HHA8VQ30"], "name": "Botany" },
      "Chemistry": { "uids": ["YLLDKRM2"], "name": "Chemistry" },
      "Zoology": { "uids": ["BSMG84MI"], "name": "Zoology" }
    }
  },
  "Jodhpur NEET UG 2026 Conquer 1 (2)": {
    "category": "NEET",
    "subjects": {
      "Physics": { "uids": ["CFKEPDCP"], "name": "Physics" },
      "Botany": { "uids": ["DECILQR1"], "name": "Botany" },
      "Chemistry": { "uids": ["356IK0CA"], "name": "Chemistry" },
      "Zoology": { "uids": ["AC17FSBR"], "name": "Zoology" }
    }
  },
  "Jodhpur NEET UG 2026 Conquer 1 Hindi": {
    "category": "NEET",
    "subjects": {
      "Physics": { "uids": ["CFKEPDCP"], "name": "Physics" },
      "Botany": { "uids": ["DECILQR1"], "name": "Botany" },
      "Chemistry": { "uids": ["356IK0CA"], "name": "Chemistry" },
      "Zoology": { "uids": ["AC17FSBR"], "name": "Zoology" }
    }
  },
  "Jodhpur NEET UG 2026 Excel 1": {
    "category": "NEET",
    "subjects": {
      "Zoology": { "uids": ["91K1MV2U"], "name": "Zoology" },
      "Botany": { "uids": ["3LPGORDJ", "GDJOQ32G"], "name": "Botany" }
    }
  },
  "Bikaner NEET UG 2026 Conquer 1": {
    "category": "NEET",
    "subjects": {
      "Chemistry": { "uids": ["4QK0ZMIK"], "name": "Chemistry" },
      "Zoology": { "uids": ["VRNIFYES"], "name": "Zoology" },
      "Physics": { "uids": ["ZQPYJ037", "H5FO4LUL"], "name": "Physics" },
      "Botany": { "uids": ["4XTK0MBI"], "name": "Botany" }
    }
  },
  "Bikaner NEET UG 2026 Conquer 2": {
    "category": "NEET",
    "subjects": {
      "Chemistry": { "uids": ["ZHDEHXAR"], "name": "Chemistry" },
      "Botany": { "uids": ["Y3JLGA8H", "NOB9Z50O"], "name": "Botany" },
      "Physics": { "uids": ["7739A622", "O7QZNZQZ"], "name": "Physics" },
      "Zoology": { "uids": ["2IFQ47M7"], "name": "Zoology" }
    }
  },
  "Bikaner NEET UG 2026 Excel 1": {
    "category": "NEET",
    "subjects": {
      "Botany": { "uids": ["VWTSQX3X"], "name": "Botany" },
      "Chemistry": { "uids": ["0T8A93DU"], "name": "Chemistry" },
      "Physics": { "uids": ["LT3Q4JBL", "ZEMXO091"], "name": "Physics" },
      "Zoology": { "uids": ["NJZYAZCK"], "name": "Zoology" }
    }
  },
  "Bikaner NEET UG 2026 Excel 2": {
    "category": "NEET",
    "subjects": {
      "Botany": { "uids": ["EDJI833V"], "name": "Botany" },
      "Chemistry": { "uids": ["K57WPS1O"], "name": "Chemistry" },
      "Zoology": { "uids": ["AEC1R14S"], "name": "Zoology" },
      "Physics": { "uids": ["2L1GWZGJ", "0SMSXWWC"], "name": "Physics" }
    }
  },
  "Bikaner NEET UG 2027 Growth 1": {
    "category": "NEET",
    "subjects": {
      "Botany": { "uids": ["M9N0ZYN8", "2QJQW66Y"], "name": "Botany" },
      "Physics": { "uids": ["74N2Q4DA", "37Y0RUNO"], "name": "Physics" },
      "Chemistry": { "uids": ["U50WGW3E"], "name": "Chemistry" },
      "Zoology": { "uids": ["BAVIZEUP"], "name": "Zoology" }
    }
  },
  "Bikaner NEET UG 2027 Growth 2": {
    "category": "NEET",
    "subjects": {
      "Physics": { "uids": ["SOUQ71B9", "VC0LG6FQ"], "name": "Physics" },
      "Chemistry": { "uids": ["NFI5HJPI", "77UFM3LV"], "name": "Chemistry" },
      "Zoology": { "uids": ["UG5E25F3"], "name": "Zoology" },
      "Botany": { "uids": ["3ZXED9BE"], "name": "Botany" }
    }
  },
  "Kota IIT JEE 2026 Conquer 1": {
    "category": "JEE",
    "subjects": {
      "Mathematics": { "uids": ["93QC7N7F"], "name": "Mathematics" },
      "Physical Chemistry": { "uids": ["G7VY8GUV"], "name": "Physical Chemistry" },
      "Organic Chemistry": { "uids": ["N2NNIPQ6"], "name": "Organic Chemistry" },
      "Physics": { "uids": ["9UG4FQ91"], "name": "Physics" }
    }
  },
  "Kota IIT JEE 2026 Conquer 2": {
    "category": "JEE",
    "subjects": {
      "Mathematics": { "uids": ["D4QMP656"], "name": "Mathematics" },
      "Inorganic Chemistry": { "uids": ["928OZ851"], "name": "Inorganic Chemistry" },
      "Organic Chemistry": { "uids": ["FKT187EB"], "name": "Organic Chemistry" },
      "Physical Chemistry": { "uids": ["DA9QSBVA"], "name": "Physical Chemistry" },
      "Physics": { "uids": ["I72NA86K"], "name": "Physics" }
    }
  },
  "Kota IIT JEE 2026 Excel 1": {
    "category": "JEE",
    "subjects": {
      "Mathematics": { "uids": ["4TT9DWSC"], "name": "Mathematics" },
      "Physics": { "uids": ["R8T0F1J8"], "name": "Physics" },
      "Organic Chemistry": { "uids": ["5U4ETVR0"], "name": "Organic Chemistry" },
      "Physical Chemistry": { "uids": ["KDQJLDXE"], "name": "Physical Chemistry" },
      "Inorganic Chemistry": { "uids": ["3MW47OCK"], "name": "Inorganic Chemistry" }
    }
  },
  "Kota IIT JEE 2026 Excel 2": {
    "category": "JEE",
    "subjects": {
      "Organic Chemistry": { "uids": ["WE0KVSGO"], "name": "Organic Chemistry" },
      "Mathematics": { "uids": ["Y0FDF7ZP"], "name": "Mathematics" },
      "Physics": { "uids": ["A0O26RUO"], "name": "Physics" },
      "Inorganic": { "uids": ["0WSTCEH1"], "name": "Inorganic" },
      "Physical Chemistry": { "uids": ["8CGN2DTT"], "name": "Physical Chemistry" }
    }
  },
  "Kota IIT JEE 2026 Excel 3": {
    "category": "JEE",
    "subjects": {
      "Physics": { "uids": ["X25IMDEE"], "name": "Physics" },
      "Mathematics": { "uids": ["XULS1U4B"], "name": "Mathematics" },
      "Organic Chemistry": { "uids": ["XG28JTAH"], "name": "Organic Chemistry" },
      "Inorganic": { "uids": ["6MSBV8NH"], "name": "Inorganic" }
    }
  },
  "Kota IIT JEE 2026 Excel 4": {
    "category": "JEE",
    "subjects": {
      "Organic Chemistry": { "uids": ["5OYR9CHE"], "name": "Organic Chemistry" },
      "Physics": { "uids": ["9L9QH7PE"], "name": "Physics" },
      "Mathematics": { "uids": ["FRT4EVM5"], "name": "Mathematics" },
      "Inorganic": { "uids": ["MZ4CLW8N"], "name": "Inorganic" },
      "Physical Chemistry": { "uids": ["RTXQG8J7"], "name": "Physical Chemistry" }
    }
  },
  "Kota IIT JEE 2026 Conquer 3": {
    "category": "JEE",
    "subjects": {
      "Chemistry": { "uids": ["GDYCEY1K"], "name": "Chemistry" },
      "Physics": { "uids": ["T3DP170V"], "name": "Physics" },
      "Mathematics": { "uids": ["ZFBR48KD"], "name": "Mathematics" }
    }
  },
  "Kota IIT JEE 2026 Conquer 4": {
    "category": "JEE",
    "subjects": {
      "Physics": { "uids": ["9JYBMMU7"], "name": "Physics" },
      "Mathematics": { "uids": ["9KNLAKAR"], "name": "Mathematics" },
      "Physical Chemistry": { "uids": ["RM3Y4RSP"], "name": "Physical Chemistry" },
      "Inorganic Chemistry": { "uids": ["BWLJJREL"], "name": "Inorganic Chemistry" },
      "Organic Chemistry": { "uids": ["GP7APCJY"], "name": "Organic Chemistry" }
    }
  },
  "Kota IIT JEE 2027 Growth 1": {
    "category": "JEE",
    "subjects": {
      "Mathematics": { "uids": ["QXGNA9E5"], "name": "Mathematics" },
      "Physical Chemistry": { "uids": ["F2FXEDXP"], "name": "Physical Chemistry" },
      "Physics": { "uids": ["B5XGXS0T"], "name": "Physics" },
      "Organic Chemistry": { "uids": ["CKYR9U9G"], "name": "Organic Chemistry" }
    }
  },
  "Kota IIT JEE 2027 Growth 2": {
    "category": "JEE",
    "subjects": {
      "Physical Chemistry": { "uids": ["CKTHUPD8"], "name": "Physical Chemistry" },
      "Physics": { "uids": ["51P0IKE4"], "name": "Physics" },
      "Mathematics": { "uids": ["O0039MPE"], "name": "Mathematics" },
      "Organic Chemistry": { "uids": ["E7JDIWZ7"], "name": "Organic Chemistry" }
    }
  },
  "Kota IIT JEE 2027 Growth 3": {
    "category": "JEE",
    "subjects": {
      "Inorganic Chemistry": { "uids": ["NBZDTVAA"], "name": "Inorganic Chemistry" },
      "Mathematics": { "uids": ["KQZTXB28"], "name": "Mathematics" },
      "Physics": { "uids": ["7NU2R53X"], "name": "Physics" }
    }
  },
  "Kota IIT JEE 2027 Growth 4": {
    "category": "JEE",
    "subjects": {
      "Physics": { "uids": ["1T2Z4X9H"], "name": "Physics" },
      "Inorganic & Physical Chemistry": { "uids": ["YXFNVQL6"], "name": "Inorganic & Physical Chemistry" },
      "Mathematics": { "uids": ["MYZKCK6Q"], "name": "Mathematics" },
      "Organic Chemistry": { "uids": ["CRR9CMEH"], "name": "Organic Chemistry" }
    }
  }
}
